kwargify_core/__init__.py
kwargify_core/cli.py
kwargify_core/config.py
kwargify_core/loader.py
kwargify_core/registry.py
kwargify_core/services.py
kwargify_core/blocks/__init__.py
kwargify_core/blocks/ai_extractor.py
kwargify_core/blocks/ai_processor.py
kwargify_core/blocks/document_template.py
kwargify_core/blocks/json_to_string.py
kwargify_core/blocks/read_file.py
kwargify_core/blocks/write_file.py
kwargify_core/core/__init__.py
kwargify_core/core/block.py
kwargify_core/core/workflow.py
kwargify_core/logging/__init__.py
kwargify_core/logging/sqlite_logger.py
kwargify_core-0.3.0.dist-info/METADATA
kwargify_core-0.3.0.dist-info/WHEEL
kwargify_core-0.3.0.dist-info/entry_points.txt
kwargify_core-0.3.0.dist-info/RECORD
