Metadata-Version: 2.4
Name: kwargify-core
Version: 0.3.0
Author-email: "lalit.gehani" <lalit.gehani@yahoo.co.in>
Requires-Python: >=3.12
Requires-Dist: jinja2<4.0.0,>=3.1.6
Requires-Dist: litellm<2.0.0,>=1.66.3
Requires-Dist: python-dotenv>=1.0.0
Requires-Dist: setuptools<80.0.0,>=79.0.0
Requires-Dist: toml>=0.10.2
Requires-Dist: typer<0.16.0,>=0.15.2
Provides-Extra: dev
Requires-Dist: hatch; extra == 'dev'
Requires-Dist: pytest-cov>=4.1.0; extra == 'dev'
Requires-Dist: pytest-mock>=3.14.0; extra == 'dev'
Requires-Dist: pytest>=7.4.0; extra == 'dev'
Requires-Dist: twine; extra == 'dev'
